[
  {
    "key": "datr",
    "value": "3wmDaBjw4hTy4q3oSGgFVQmh",
    "domain": "facebook.com",
    "path": "\/",
    "hostOnly": false,
    "creation": "2025-08-07T06:43:42.964Z",
    "lastAccessed": "2025-08-07T06:43:42.965Z"
  },
  {
    "key": "sb",
    "value": "3wmDaMP8BO5Hf1L4oSLSiXZM",
    "domain": "facebook.com",
    "path": "\/",
    "hostOnly": false,
    "creation": "2025-08-07T06:43:42.966Z",
    "lastAccessed": "2025-08-07T06:43:42.966Z"
  },
  {
    "key": "m_pixel_ratio",
    "value": "2.206249952316284",
    "domain": "facebook.com",
    "path": "\/",
    "hostOnly": false,
    "creation": "2025-08-07T06:43:42.966Z",
    "lastAccessed": "2025-08-07T06:43:42.967Z"
  },
  {
    "key": "wd",
    "value": "490x1061",
    "domain": "facebook.com",
    "path": "\/",
    "hostOnly": false,
    "creation": "2025-08-07T06:43:42.967Z",
    "lastAccessed": "2025-08-07T06:43:42.967Z"
  },
  {
    "key": "c_user",
    "value": "61578273281792",
    "domain": "facebook.com",
    "path": "\/",
    "hostOnly": false,
    "creation": "2025-08-07T06:43:42.967Z",
    "lastAccessed": "2025-08-07T06:43:42.967Z"
  },
  {
    "key": "xs",
    "value": "21%3AxvoDUE0pcfK6Yg%3A2%3A1753418268%3A-1%3A-1",
    "domain": "facebook.com",
    "path": "\/",
    "hostOnly": false,
    "creation": "2025-08-07T06:43:42.968Z",
    "lastAccessed": "2025-08-07T06:43:42.968Z"
  },
  {
    "key": "pas",
    "value": "61578273281792%3ARQcp97UfCt",
    "domain": "facebook.com",
    "path": "\/",
    "hostOnly": false,
    "creation": "2025-08-07T06:43:42.968Z",
    "lastAccessed": "2025-08-07T06:43:42.968Z"
  },
  {
    "key": "vpd",
    "value": "v1%3B945x489x2.206249952316284",
    "domain": "facebook.com",
    "path": "\/",
    "hostOnly": false,
    "creation": "2025-08-07T06:43:42.969Z",
    "lastAccessed": "2025-08-07T06:43:42.969Z"
  },
  {
    "key": "ps_l",
    "value": "1",
    "domain": "facebook.com",
    "path": "\/",
    "hostOnly": false,
    "creation": "2025-08-07T06:43:42.969Z",
    "lastAccessed": "2025-08-07T06:43:42.969Z"
  },
  {
    "key": "ps_n",
    "value": "1",
    "domain": "facebook.com",
    "path": "\/",
    "hostOnly": false,
    "creation": "2025-08-07T06:43:42.970Z",
    "lastAccessed": "2025-08-07T06:43:42.970Z"
  },
  {
    "key": "locale",
    "value": "en_US",
    "domain": "facebook.com",
    "path": "\/",
    "hostOnly": false,
    "creation": "2025-08-07T06:43:42.970Z",
    "lastAccessed": "2025-08-07T06:43:42.971Z"
  },
  {
    "key": "fbl_st",
    "value": "101318696%3BT%3A29240793",
    "domain": "facebook.com",
    "path": "\/",
    "hostOnly": false,
    "creation": "2025-08-07T06:43:42.971Z",
    "lastAccessed": "2025-08-07T06:43:42.972Z"
  },
  {
    "key": "wl_cbv",
    "value": "v2%3Bclient_version%3A2886%3Btimestamp%3A1754447613",
    "domain": "facebook.com",
    "path": "\/",
    "hostOnly": false,
    "creation": "2025-08-07T06:43:42.972Z",
    "lastAccessed": "2025-08-07T06:43:42.972Z"
  },
  {
    "key": "fr",
    "value": "081Kz7lZu7wrTGnXd.AWfLU93ZfFPCXoWuEfRcmxTPrlxTJE7QPh5CnrqXkcccdc8uzUo.Bogwnf..AAA.0.0.Bok_a1.AWfKyHMcRkqP8r5LqAAVSm73O10",
    "domain": "facebook.com",
    "path": "\/",
    "hostOnly": false,
    "creation": "2025-08-07T06:43:42.973Z",
    "lastAccessed": "2025-08-07T06:43:42.973Z"
  }
]
